ccid/__init__.py
ccid/bulk_in_messages.py
ccid/bulk_message.py
ccid/bulk_out_messages.py
ccid/descriptors.py
common/__init__.py
common/ber.py
common/binary.py
common/bitstr.py
common/hstr.py
common/intlist.py
common/parserc.py
common/str.py
crypto/__init__.py
crypto/des.py
crypto/modes.py
emv/__init__.py
emv/commands.py
emv/data.py
emv/dsc.py
emv/key_management.py
emv/records.py
examples/__init__.py
examples/emv_key_derivation.py
examples/evc_cvc3.py
examples/evc_dcvv.py
gep3-0.4.7.dist-info/licenses/LICENSE
globalplatform/__init__.py
globalplatform/commands.py
globalplatform/encodings.py
globalplatform/key_management.py
globalplatform/scp02.py
iso7816/__init__.py
iso7816/apdu.py
iso7816/commands.py
iso7816/encodings.py
multos/__init__.py
multos/commands.py
multos/encodings.py
tests/__init__.py
tests/test_common_ber.py
tests/test_crypto_des.py
gep3-0.4.7.dist-info/METADATA
gep3-0.4.7.dist-info/WHEEL
gep3-0.4.7.dist-info/top_level.txt
gep3-0.4.7.dist-info/RECORD
