Metadata-Version: 2.4
Name: gep3
Version: 0.4.7
Summary: Generic Encryption Peripheral: various utilities related to cryptography and smart cards
Home-page: https://github.com/spochic/gep3
Author: Sebastien Pochic
Author-email: spochic@gmail.com
Project-URL: Bug Tracker, https://github.com/spochic/gep3/issues
Classifier: Programming Language :: Python :: 3
Classifier: License :: OSI Approved :: MIT License
Classifier: Operating System :: OS Independent
Classifier: Development Status :: 3 - Alpha
Classifier: Topic :: Security :: Cryptography
Classifier: Topic :: System :: Hardware :: Universal Serial Bus (USB) :: Smart Card
Requires-Python: >=3.11
License-File: LICENSE
Requires-Dist: parsec
Dynamic: license-file
